flatrtree-1.0.0rc2.dist-info/METADATA
flatrtree-1.0.0rc2.dist-info/WHEEL
flatrtree-1.0.0rc2.dist-info/RECORD
flatrtree-1.0.0rc2.dist-info/top_level.txt
flatrtree-1.0.0rc2.dist-info/LICENSE
flatrtree/box_dist.c
flatrtree/hilbert_builder.cpp
flatrtree/py.typed
flatrtree/rtree.py
flatrtree/__init__.py
flatrtree/omt_builder.cpp
flatrtree/omt_builder.pypy39-pp73-x86-linux-gnu.so
flatrtree/box_dist.pypy39-pp73-x86-linux-gnu.so
flatrtree/__init__.pyi
flatrtree/hilbert_builder.pypy39-pp73-x86-linux-gnu.so
flatrtree/serialization.py
flatrtree/internal/flatrtree_pb2.pyi
flatrtree/internal/__init__.py
flatrtree/internal/flatrtree_pb2.py
