Metadata-Version: 2.1
Name: flatrtree
Version: 1.0.0rc2
Summary: Tiny, portable R-trees.
Home-page: https://github.com/flatrtree/flatrtree-py
Author: Daniel Whalen
Author-email: daniel.r.whalen@gmail.com
License: MIT
Requires-Python: >=3.7
License-File: LICENSE
Requires-Dist: protobuf
Provides-Extra: ci
Requires-Dist: black ; extra == 'ci'
Requires-Dist: isort ; extra == 'ci'
Requires-Dist: mypy ; extra == 'ci'
Requires-Dist: types-protobuf ; extra == 'ci'
Provides-Extra: test
Requires-Dist: pytest ; extra == 'test'
Requires-Dist: pytest-subtests ; extra == 'test'
